<annotation>
	<folder>train</folder>
	<filename>20191017_100856.jpg</filename>
	<path>C:\tensorflow5\models\research\object_detection\images\train\20191017_100856.jpg</path>
	<source>
		<database>Unknown</database>
	</source>
	<size>
		<width>960</width>
		<height>720</height>
		<depth>3</depth>
	</size>
	<segmented>0</segmented>
	<object>
		<name>pod</name>
		<pose>Unspecified</pose>
		<truncated>0</truncated>
		<difficult>0</difficult>
		<bndbox>
			<xmin>374</xmin>
			<ymin>176</ymin>
			<xmax>782</xmax>
			<ymax>546</ymax>
		</bndbox>
	</object>
</annotation>
